cachette/__init__.py
cachette/backends/__init__.py
cachette/backends/dynamodb.py
cachette/backends/inmemory.py
cachette/backends/memcached.py
cachette/backends/mongodb.py
cachette/backends/pickle.py
cachette/backends/redis.py
cachette/cachette_config.py
cachette/codecs/__init__.py
cachette/codecs/dataframe/csv.py
cachette/codecs/dataframe/feather.py
cachette/codecs/dataframe/parquet.py
cachette/codecs/json.py
cachette/codecs/msgpack.py
cachette/codecs/orjson.py
cachette/codecs/pickle.py
cachette/codecs/vanilla.py
cachette/core.py
cachette/load_config.py
cachette-0.1.8.dist-info/LICENSE
cachette-0.1.8.dist-info/METADATA
cachette-0.1.8.dist-info/WHEEL
cachette-0.1.8.dist-info/RECORD
