Metadata-Version: 2.1
Name: cachette
Version: 0.1.8
Summary: Cache extension for ASGI frameworks
Home-page: https://github.com/aekasitt/cachette
License: MIT
Keywords: starlette,fastapi,cache,redis,aioredis,dynamodb,aiobotocore,asynchronous,memcached,aiomcache,mongodb,motor,pymongo
Author: Sitt Guruvanich
Author-email: aekazitt+github@gmail.com
Requires-Python: >=3.9,<4.0
Classifier: Environment :: Web Environment
Classifier: Intended Audience :: Developers
Classifier: License :: OSI Approved :: MIT License
Classifier: Operating System :: OS Independent
Classifier: Programming Language :: Python :: 3
Classifier: Programming Language :: Python :: 3.9
Classifier: Programming Language :: Python :: 3.10
Classifier: Programming Language :: Python :: 3.11
Classifier: Programming Language :: Python :: 3.12
Classifier: Programming Language :: Python :: 3 :: Only
Classifier: Programming Language :: Python :: 3.13
Classifier: Topic :: Internet :: WWW/HTTP :: Dynamic Content
Classifier: Topic :: Software Development :: Libraries :: Python Modules
Requires-Dist: pydantic (>=2.4.0,<3.0.0)
Project-URL: Repository, https://github.com/aekasitt/cachette
